nautilus_namecodes/__main__.py
nautilus_namecodes/_helpers.py
nautilus_namecodes/_version.py
nautilus_namecodes/builder/namecode_builder_dataclasses.py
nautilus_namecodes/format/generate_console.py
nautilus_namecodes/main.py
nautilus_namecodes/namecodes_dataclasses.py
nautilus_namecodes/scheme/v_0_0_1/namecode_values.py
nautilus_namecodes/scheme/v_0_0_1/namecodes.py
nautilus_namecodes-0.3.0.dist-info/entry_points.txt
nautilus_namecodes-0.3.0.dist-info/LICENSE.md
nautilus_namecodes-0.3.0.dist-info/WHEEL
nautilus_namecodes-0.3.0.dist-info/METADATA
nautilus_namecodes-0.3.0.dist-info/RECORD
