Metadata-Version: 2.1
Name: nautilus-namecodes
Version: 0.3.0
Summary: Nautilus Filename Specification (nautilus-namecodes)
Home-page: https://github.com/da2ce7/nautilus-filename_specification
License: AGPL-3.0-only
Author: Cameron Garnham
Author-email: cameron@nautilus-cyberneering.de
Maintainer: Cameron Garnham
Maintainer-email: cameron@nautilus-cyberneering.de
Requires-Python: >=3.9,<4.0
Classifier: Development Status :: 1 - Planning
Classifier: License :: OSI Approved :: GNU Affero General Public License v3
Classifier: Natural Language :: English
Classifier: Operating System :: POSIX
Classifier: Programming Language :: Python :: 3
Classifier: Programming Language :: Python :: 3.10
Classifier: Programming Language :: Python :: 3.9
Requires-Dist: atoml (>=1.1.0,<2.0.0)
Requires-Dist: tox (>=3.24.4,<4.0.0)
Requires-Dist: typer[all] (>=0.4.0,<0.5.0)
Project-URL: Repository, https://github.com/da2ce7/nautilus-filename_specification
